sphinx_nose-0.3.1.dist-info/DESCRIPTION.rst
sphinx_nose-0.3.1.dist-info/METADATA
sphinx_nose-0.3.1.dist-info/RECORD
sphinx_nose-0.3.1.dist-info/WHEEL
sphinx_nose-0.3.1.dist-info/entry_points.txt
sphinx_nose-0.3.1.dist-info/metadata.json
sphinx_nose-0.3.1.dist-info/top_level.txt
sphinxnose/__init__.py
sphinxnose/finders.py
sphinxnose/plugin.py
sphinxnose/sphinx.py
