Metadata-Version: 2.0
Name: sphinx-nose
Version: 0.3.1
Summary: Run Sphinx doctests in Nose.
Home-page: https://github.com/uranusjr/saim-al-dahr
Author: Tzu-ping Chung
Author-email: uranusjr@gmail.com
License: MIT
Keywords: doctest,nose,sphinx
Platform: UNKNOWN
Classifier: Development Status :: 2 - Pre-Alpha
Classifier: Intended Audience :: Developers
Classifier: License :: OSI Approved :: MIT License
Classifier: Natural Language :: English
Classifier: Programming Language :: Python :: 2
Classifier: Programming Language :: Python :: 2.7
Classifier: Programming Language :: Python :: 3
Classifier: Programming Language :: Python :: 3.3
Classifier: Programming Language :: Python :: 3.4
Requires-Dist: nose
Requires-Dist: six
Requires-Dist: sphinx
